mzcn/__init__.py
mzcn/version.py
mzcn/auto/__init__.py
mzcn/auto/preparer/__init__.py
mzcn/auto/preparer/prepare.py
mzcn/auto/preparer/preparer.py
mzcn/auto/tuner/__init__.py
mzcn/auto/tuner/tune.py
mzcn/auto/tuner/tuner.py
mzcn/data_pack/__init__.py
mzcn/data_pack/data_pack.py
mzcn/data_pack/pack.py
mzcn/dataloader/__init__.py
mzcn/dataloader/dataloader.py
mzcn/dataloader/dataloader_builder.py
mzcn/dataloader/dataset.py
mzcn/dataloader/dataset_builder.py
mzcn/dataloader/callbacks/__init__.py
mzcn/dataloader/callbacks/histogram.py
mzcn/dataloader/callbacks/lambda_callback.py
mzcn/dataloader/callbacks/ngram.py
mzcn/dataloader/callbacks/padding.py
mzcn/datasets/__init__.py
mzcn/datasets/embeddings/__init__.py
mzcn/datasets/embeddings/load_fasttext_embedding.py
mzcn/datasets/embeddings/load_glove_embedding.py
mzcn/datasets/quora_qp/__init__.py
mzcn/datasets/quora_qp/load_data.py
mzcn/datasets/snli/__init__.py
mzcn/datasets/snli/load_data.py
mzcn/datasets/toy/__init__.py
mzcn/datasets/wiki_qa/__init__.py
mzcn/datasets/wiki_qa/load_data.py
mzcn/embedding/__init__.py
mzcn/embedding/embedding.py
mzcn/engine/__init__.py
mzcn/engine/base_callback.py
mzcn/engine/base_metric.py
mzcn/engine/base_model.py
mzcn/engine/base_preprocessor.py
mzcn/engine/base_task.py
mzcn/engine/hyper_spaces.py
mzcn/engine/param.py
mzcn/engine/param_table.py
mzcn/losses/__init__.py
mzcn/losses/rank_cross_entropy_loss.py
mzcn/losses/rank_hinge_loss.py
mzcn/metrics/__init__.py
mzcn/metrics/accuracy.py
mzcn/metrics/average_precision.py
mzcn/metrics/cross_entropy.py
mzcn/metrics/discounted_cumulative_gain.py
mzcn/metrics/mean_average_precision.py
mzcn/metrics/mean_reciprocal_rank.py
mzcn/metrics/normalized_discounted_cumulative_gain.py
mzcn/metrics/precision.py
mzcn/models/__init__.py
mzcn/models/anmm.py
mzcn/models/arci.py
mzcn/models/arcii.py
mzcn/models/bert.py
mzcn/models/bimpm.py
mzcn/models/cdssm.py
mzcn/models/conv_knrm.py
mzcn/models/dense_baseline.py
mzcn/models/diin.py
mzcn/models/drmm.py
mzcn-1.0.8.dist-info/LICENSE
mzcn-1.0.8.dist-info/LICENSE.baiduyun.uploading.cfg
mzcn-1.0.8.dist-info/METADATA
mzcn-1.0.8.dist-info/WHEEL
mzcn-1.0.8.dist-info/top_level.txt
mzcn-1.0.8.dist-info/RECORD
