Metadata-Version: 2.1
Name: mzcn
Version: 1.0.8
Summary: matchzoo-py的中文语料改造版本，更合适搭建中文语料的深度学习匹配模型
Home-page: https://github.com/yingdajun/mzcn/
Author: mzcn Authors:英俊
Author-email: 2227495940@qq.com
License: Apache 2.0
Keywords: text matching models
Platform: UNKNOWN
Classifier: Development Status :: 3 - Alpha
Classifier: Environment :: Console
Classifier: Operating System :: POSIX :: Linux
Classifier: Topic :: Scientific/Engineering :: Artificial Intelligence
Classifier: License :: OSI Approved :: Apache Software License
Classifier: Programming Language :: Python :: 3.6
License-File: LICENSE
License-File: LICENSE.baiduyun.uploading.cfg
Requires-Dist: torch (>=1.5.0)
Requires-Dist: pytorch-transformers (>=1.1.0)
Requires-Dist: nltk (>=3.4.3)
Requires-Dist: numpy (>=1.16.4)
Requires-Dist: tqdm (==4.38.0)
Requires-Dist: dill (>=0.2.9)
Requires-Dist: pandas (>=1.3.1)
Requires-Dist: networkx (>=2.3)
Requires-Dist: h5py (>=2.9.0)
Requires-Dist: hyperopt (==0.1.2)
Requires-Dist: jieba (>=0.39)
Requires-Dist: opencc (==1.1.1)
Provides-Extra: tests
Requires-Dist: coverage (>=4.5.3) ; extra == 'tests'
Requires-Dist: codecov (>=2.0.15) ; extra == 'tests'
Requires-Dist: pytest (>=4.6.3) ; extra == 'tests'
Requires-Dist: pytest-cov (>=2.7.1) ; extra == 'tests'
Requires-Dist: flake8 (>=3.7.7) ; extra == 'tests'
Requires-Dist: flake8-docstrings (>=1.3.0) ; extra == 'tests'
